{
    "general_questions": [
        "Batuk?",
        "Berat badan menurun?",
        "Bercak kulit?",
        "Berkeringat di malam hari?",
        "Bintik koplik (bintik-bintik putih kecil di dalam mulut, khususnya di bagian dalam pipi)?",
        "Buang air besar berdarah?",
        "Buang air besar berwarna hitam?",
        "Cenderung perfeksionis?",
        "Meriang dalam jangka waktu yang panjang?",
        "Demam?",
        "Denyut nadi yang melemah hingga 100 kali per menit?",
        "Detak jantung yang tidak teratur?",
        "Detak jantung berdebar-debar?",
        "Diare?",
        "Sulit buang air besar?",
        "Disabilitas tanpa riwayat kecelakaan?",
        "Deformitas tanpa riwayat kecelakaan?",
        "Emosi yang mudah terpengaruh?",
        "Feses cair?",
        "Feses encer?",
        "Mengalami kecemasan?",
        "Depresi?",
        "Gatal-gatal pada kulit?",
        "Gusi berdarah?",
        "Hilangnya indra penciuman?",
        "Hilangnya indra rasa?",
        "Kehilangan gairah seksual?",
        "Kehilangan jalur pemikiran saat berbicara?",
        "Kelainan kulit (biasanya terjadi di bagian tubuh yang terbuka seperti kaki, tangan, leher dan wajah)?",
        "Kelebihan kebiruan pada bibir?",
        "Kelebihan kebiruan pada ujung kuku?",
        "Kelelahan? (lethargy)",
        "Kelemahan?",
        "Kesemutan pada anggota gerak?",
        "Rasa tertusuk-tusuk pada anggota gerak?",
        "Nyeri pada anggota gerak?",
        "Kesulitan berbicara?",
        "Kesulitan dalam navigasi?",
        "Kesulitan dalam pemahaman ruang?",
        "Kesulitan dalam perencanaan?",
        "Kesulitan dalam menyelesaikan tugas?",
        "Kesulitan menelan makanan?",
        "Kesulitan menelan minuman?",
        "Kondisi kulit seperti bintik-bintik ungu?",
        "Kondisi kulit seperti luka yang tidak sembuh?",
        "Konjungtivitis (mata merah, mata bisa menjadi sensitif terhadap cahaya)?",
        "Kram perut?",
        "Nyeri perut?",
        "Kulit atau mata yang menguning (ikterus, jaundice)?",
        "Kulit pucat?",
        "Kulit tampak keriput?",
        "Kulit yang tidak berkeringat?",
        "Alis mata rontok?",
        "Lemas (lesu)?",
        "Lepuh pada tangan?",
        "Lepuh pada kaki?",
        "Luka tidak nyeri pada tangan?",
        "Luka tidak nyeri pada kaki?",
        "Mata iritasi?",
        "Memiliki citra diri yang negatif?",
        "Memiliki kekhawatiran berlebihan tentang masa depan?",
        "Mengalami kesulitan dalam mengelola stres?",
        "Menggigil?",
        "Mengi? (suara mengi atau bersiul yang dihasilkan saat bernapas)",
        "Mimisan?",
        "Mual?",
        "Muntah?",
        "Perut kembung?",
        "Mudah berdarah?",
        "Mudah memar?",
        "Mudah lelah?",
        "Munculnya eschar atau jaringan hitam pada kulit?",
        "Munculnya garis merah kecil?",
        "Nafsu makan menurun?",
        "Nyeri punggung?",
        "Nyeri lengan?",
        "Ketidaknyamanan di atas bagian atas perut?",
        "Ketidaknyamanan di punggung?",
        "Ketidaknyamanan di lengan?",
        "Nyeri dada?",
        "Nyeri otot?",
        "Nyeri di belakang mata?",
        "Nyeri tulang?",
        "Nyeri kepala?",
        "Nyeri pada persendian?",
        "Nyeri pada saraf tepi?",
        "Pembengkakan kelenjar limfa (getah bening)?",
        "Penarikan diri dari aktivitas sosial?",
        "Penebalan wajah?",
        "Penebalan cuping telinga?",
        "Pertumbuhan terhambat (pada anak-anak)?",
        "Perubahan mood?",
        "Perubahan kepribadian?",
        "Perut bengkak?",
        "Perut membuncit?",
        "Pilek?",
        "Produksi dahak setiap pagi akibat penumpukan dahak berlebih di paru-paru?",
        "Pusing?",
        "Pingsan?",
        "Rambut mudah rontok?",
        "Rambut tampak seperti rambut jagung?",
        "Rasa sesak di dada?",
        "Riwayat gangguan makan saat masa kanak-kanak?",
        "Ruam?",
        "Sakit perut hebat?",
        "Sakit tenggorokan?",
        "Sesak napas (kesulitan bernapas, napas pendek)?",
        "Suhu tubuh menurun?",
        "Tubuh terasa dingin?",
        "Tampak bengkak?",
        "Tampak kurus?",
        "Timbul bintik-bintik merah pada kulit?",
        "Tinja berwarna pucat?",
        "Tulang rapuh?",
        "Deformitas tulang?",
        "Tulang-tulang di tubuh terlihat jelas?",
        "Tungkai membesar?",
        "Ulkus sulit sembuh?",
        "Urgensi untuk buang air besar?",
        "Urin berwarna gelap?"
    ],
    "question_branches": [
        {
            "question": "Batuk?",
            "child_question": "Batuk pada dini hari?"
        },
        {
            "question": "Batuk?",
            "child_question": "Batuk pada malam hari?"
        },
        {
            "question": "Batuk dengan dahak berwarna kuning?",
            "child_question": "Batuk berdahak dengan cairan mengandung nanah yang berwarna kekuningan?"
        },
        {
            "question": "Batuk?",
            "child_question": "Batuk kronis?"
        },
        {
            "question": "Berat badan menurun?",
            "child_question": "Penurunan berat badan yang tidak dapat dijelaskan?"
        },
        {
            "question": "Berat badan menurun?",
            "child_question": "Penurunan berat badan yang tidak disengaja?"
        },
        {
            "question": "Berkeringat di malam hari?",
            "child_question": "Berkeringat di malam hari meski tanpa melakukan kegiatan?"
        },
        {
            "question": "Demam berlangsung lebih dari seminggu?",
            "child_question": "Demam berlangsung hingga tiga minggu?"
        },
        {
            "question": "Demam?",
            "child_question": "Demam berkepanjangan?"
        },
        {
            "question": "Demam berlangsung 2-7 hari?",
            "child_question": "Demam berlangsung terus-menerus selama 2-7 hari kemudian turun dengan cepat?"
        },
        {
            "question": "Demam?",
            "child_question": "Demam mendadak?"
        },
        {
            "question": "Demam?",
            "child_question": "Demam meningkat secara bertahap setiap harinya?"
        },
        {
            "question": "Demam?",
            "child_question": "Demam ringan?"
        },
        {
            "question": "Demam?",
            "child_question": "Demam tinggi?"
        },
        {
            "question": "Demam?",
            "child_question": "Demam tidak merespon terhadap obat penurun panas?"
        },
        {
            "question": "Diare?",
            "child_question": "Diare berkepanjangan?"
        },
        {
            "question": "Infeksi?",
            "child_question": "Infeksi yang sering terjadi (berulang)?"
        },
        {
            "question": "Infeksi yang sering terjadi (berulang)?",
            "child_question": "Infeksi berulang, terutama pada kulit, gusi, atau saluran kemih?"
        },
        {
            "question": "Infeksi yang sering terjadi (berulang)?",
            "child_question": "Infeksi pernapasan berulang (sering terjadi)?"
        },
        {
            "question": "Infeksi jamur di mulut, tenggorokan, atau vagina?"
        },
        {
            "question": "Kelelahan? (lethargy)",
            "child_question": "Kelelahan kronis?"
        },
        {
            "question": "Kelelahan? (lethargy)",
            "child_question": "Kelelahan yang berkelanjutan (persisten)?"
        },
        {
            "question": "Kelelahan? (lethargy)",
            "child_question": "Kelelahan yang tidak dapat dijelaskan?"
        },
        {
            "question": "Kelelahan? (lethargy)",
            "child_question": "Kelelahan yang tidak wajar?"
        }
    ],
    "group_branches": [
        {
            "question": "Batuk?",
            "group": "Jenis Batuk"
        },
        {
            "question": "Batuk berdahak?",
            "group": "Jenis Dahak Batuk"
        },
        {
            "question": "Demam?",
            "group": "Durasi Demam"
        },
        {
            "question": "Demam?",
            "group": "Suhu Demam"
        }
    ],
    "group_questions": [
        {
            "group": "Jenis Batuk",
            "question": "Batuk kering?"
        },
        {
            "group": "Jenis Batuk",
            "question": "Batuk berdahak?"
        },
        {
            "group": "Jenis Dahak Batuk",
            "question": "Batuk dengan dahak berwarna jernih?"
        },
        {
            "group": "Jenis Dahak Batuk",
            "question": "Batuk dengan dahak berwarna putih?"
        },
        {
            "group": "Jenis Dahak Batuk",
            "question": "Batuk dengan dahak berwarna kuning?"
        },
        {
            "group": "Jenis Dahak Batuk",
            "question": "Batuk dengan dahak berwarna hijau?"
        },
        {
            "group": "Jenis Dahak Batuk",
            "question": "Ketika batuk terkadang dahak bercampur darah?"
        },
        {
            "group": "Durasi Demam",
            "question": "Demam berlangsung kurang dari dua hari?"
        },
        {
            "group": "Durasi Demam",
            "question": "Demam berlangsung 2-7 hari?"
        },
        {
            "group": "Durasi Demam",
            "question": "Demam berlangsung 1-2 minggu?"
        },
        {
            "group": "Durasi Demam",
            "question": "Demam berlangsung hingga 3 minggu?"
        },
        {
            "group": "Suhu Demam",
            "question": "Suhu demam kurang dari 39 derajat Celcius?"
        },
        {
            "group": "Suhu Demam",
            "question": "Suhu demam 39 derajat Celcius?"
        },
        {
            "group": "Suhu Demam",
            "question": "Suhu demam mencapai 40 derajat Celcius?"
        }
    ]
}